map_kit-1.0.data/scripts/myfreeport
map_kit-1.0.dist-info/DESCRIPTION.rst
map_kit-1.0.dist-info/METADATA
map_kit-1.0.dist-info/RECORD
map_kit-1.0.dist-info/WHEEL
map_kit-1.0.dist-info/metadata.json
map_kit-1.0.dist-info/top_level.txt
mapkit/__init__.py
mapkit/ident.py
mapkit/map_xyz.py
mapkit/pipehtml.py
mapkit/postgis_interface.py
mapkit/quickmaps.py
