Metadata-Version: 2.0
Name: map-kit
Version: 1.0
Summary: A Python library for map integration.
Home-page: https://github.com/murphy214/mapkit
Author: Bennett Murphy
Author-email: murphy214@live.marshall.edu
License: UNKNOWN
Platform: UNKNOWN
Requires-Dist: enum
Requires-Dist: future
Requires-Dist: geopandas
Requires-Dist: ipython (<6.0)
Requires-Dist: mercantile
Requires-Dist: numpy
Requires-Dist: pandas
Requires-Dist: psycopg2
Requires-Dist: python-geohash (>=0.8.5)
Requires-Dist: simplejson
